four_letter_blocks/__init__.py
four_letter_blocks/__main__.py
four_letter_blocks/big_puzzle_pair.py
four_letter_blocks/block.py
four_letter_blocks/block_packer.py
four_letter_blocks/clue.py
four_letter_blocks/clue_painter.py
four_letter_blocks/evo.py
four_letter_blocks/evo_packer.py
four_letter_blocks/fill_thread.py
four_letter_blocks/focused_plain_text_edit.py
four_letter_blocks/four_letter_blocks_rc.py
four_letter_blocks/grid.py
four_letter_blocks/line_deduper.py
four_letter_blocks/main_window.py
four_letter_blocks/puzzle.py
four_letter_blocks/puzzle_pair.py
four_letter_blocks/puzzle_set.py
four_letter_blocks/square.py
four_letter_blocks/suit.py
four_letter_blocks-1.3.0.dist-info/LICENSE
four_letter_blocks-1.3.0.dist-info/METADATA
four_letter_blocks-1.3.0.dist-info/WHEEL
four_letter_blocks-1.3.0.dist-info/entry_points.txt
four_letter_blocks-1.3.0.dist-info/top_level.txt
four_letter_blocks-1.3.0.dist-info/RECORD
