Metadata-Version: 2.1
Name: four-letter-blocks
Version: 1.3.0
Summary: Crossword puzzle assembled from blocks of four letters
Home-page: https://donkirkby.github.io/four-letter-blocks/
Author: Don Kirkby
Project-URL: Bug Reports, https://github.com/donkirkby/four-letter-blocks/issues
Project-URL: Source, https://github.com/donkirkby/four-letter-blocks
Keywords: puzzle wordgame crossword
Classifier: Development Status :: 5 - Production/Stable
Classifier: Intended Audience :: End Users/Desktop
Classifier: Topic :: Games/Entertainment :: Puzzle Games
Classifier: License :: OSI Approved :: MIT License
Classifier: Programming Language :: Python :: 3.10
License-File: LICENSE
Requires-Dist: PySide6
Requires-Dist: numpy
Requires-Dist: colorspacious
Provides-Extra: dev
Requires-Dist: pytest ; extra == 'dev'
Requires-Dist: coverage ; extra == 'dev'
Requires-Dist: space-tracer ; extra == 'dev'
